simple_diceware/__init__.py
simple_diceware/eff_large_wordlist.txt
simple_diceware/simple_diceware.py
simple_diceware-0.4.1.dist-info/entry_points.txt
simple_diceware-0.4.1.dist-info/LICENSE
simple_diceware-0.4.1.dist-info/WHEEL
simple_diceware-0.4.1.dist-info/METADATA
simple_diceware-0.4.1.dist-info/RECORD
