Metadata-Version: 2.1
Name: simple-diceware
Version: 0.4.1
Summary: Create diceware passwords from the command line
Home-page: https://github.com/bchopson/simple-diceware
License: MIT
Author: Ben Chopson
Author-email: bchopson@users.noreply.github.com
Requires-Python: >=3.6,<4.0
Classifier: License :: OSI Approved :: MIT License
Classifier: Programming Language :: Python :: 3
Classifier: Programming Language :: Python :: 3.6
Classifier: Programming Language :: Python :: 3.7
Classifier: Programming Language :: Python :: 3.8
Project-URL: Repository, https://github.com/bchopson/simple-diceware
